square_authentication/__init__.py
square_authentication/configuration.py
square_authentication/data/config.sample.ini
square_authentication/data/config.testing.sample.ini
square_authentication/main.py
square_authentication/messages.py
square_authentication/pydantic_models/__init__.py
square_authentication/pydantic_models/core.py
square_authentication/pydantic_models/internal.py
square_authentication/pydantic_models/profile.py
square_authentication/routes/__init__.py
square_authentication/routes/core.py
square_authentication/routes/internal.py
square_authentication/routes/profile.py
square_authentication/utils/__init__.py
square_authentication/utils/core.py
square_authentication/utils/encryption.py
square_authentication/utils/routes/__init__.py
square_authentication/utils/routes/core.py
square_authentication/utils/routes/internal.py
square_authentication/utils/routes/profile.py
square_authentication/utils/token.py
square_authentication-11.2.2.dist-info/WHEEL
square_authentication-11.2.2.dist-info/METADATA
square_authentication-11.2.2.dist-info/RECORD
